imajin.py
imajin-1.4.0.dist-info/METADATA
imajin-1.4.0.dist-info/WHEEL
imajin-1.4.0.dist-info/entry_points.txt
imajin-1.4.0.dist-info/licenses/LICENSE.txt
imajin-1.4.0.dist-info/RECORD
