Metadata-Version: 2.4
Name: imajin
Version: 1.4.0
Summary: Search tool for Japanese text in EPUB and Mokuro files
Project-URL: Repository, https://github.com/YonKuma/imajin.py
Author-email: YonKuma <kumarei@gmail.com>
License-Expression: CC-PDDC
License-File: LICENSE.txt
Keywords: ebook,example-sentences,japanese,manga,text-search
Classifier: Environment :: Console
Classifier: Intended Audience :: End Users/Desktop
Classifier: Natural Language :: Japanese
Classifier: Programming Language :: Python
Classifier: Programming Language :: Python :: 3
Classifier: Programming Language :: Python :: 3.9
Classifier: Programming Language :: Python :: 3.10
Classifier: Programming Language :: Python :: 3.11
Classifier: Programming Language :: Python :: 3.12
Classifier: Topic :: Utilities
Requires-Python: >=3.9
Requires-Dist: beautifulsoup4
Requires-Dist: lxml
Requires-Dist: mecab-python3
Requires-Dist: unidic-lite
